[
  {
    "id": 129395818,
    "status": 1,
    "score": 0,
    "tags": "",
    "is_rereading": 0,
    "num_read_chapters": 96,
    "num_read_volumes": 0,
    "created_at": 1657766875,
    "manga_title": "Ao no Hako",
    "manga_english": "Blue Box",
    "manga_num_chapters": 0,
    "manga_num_volumes": 0,
    "manga_publishing_status": 1,
    "manga_id": 135545,
    "manga_magazines": null,
    "manga_total_members": 65081,
    "manga_total_scores": 22616,
    "manga_score_val": 8.08,
    "manga_score_diff": -99,
    "manga_popularity": 248,
    "genres": [
      {
        "id": 22,
        "name": "Romance"
      },
      {
        "id": 30,
        "name": "Sports"
      }
    ],
    "demographics": [
      {
        "id": 27,
        "name": "Shounen"
      }
    ],
    "title_localized": null,
    "manga_url": "/manga/135545/Ao_no_Hako",
    "manga_image_path": "https://cdn.myanimelist.net/r/192x272/images/manga/2/248748.jpg?s=e1c8b22bb42adeb0d05183daae93d013",
    "is_added_to_list": false,
    "manga_media_type_string": "Manga",
    "start_date_string": "07-13-22",
    "finish_date_string": null,
    "manga_start_date_string": "04-12-21",
    "manga_end_date_string": null,
    "days_string": 741,
    "retail_string": null,
    "priority_string": "Low",
    "notes": "",
    "editable_notes": ""
  },
  {
    "id": 132155342,
    "status": 1,
    "score": 0,
    "tags": "",
    "is_rereading": 0,
    "num_read_chapters": 117,
    "num_read_volumes": 0,
    "created_at": 1662260497,
    "manga_title": "Boku no Kokoro no Yabai Yatsu",
    "manga_english": "The Dangers in My Heart",
    "manga_num_chapters": 0,
    "manga_num_volumes": 0,
    "manga_publishing_status": 1,
    "manga_id": 112807,
    "manga_magazines": null,
    "manga_total_members": 51569,
    "manga_total_scores": 17499,
    "manga_score_val": 8.23,
    "manga_score_diff": -99,
    "manga_popularity": 320,
    "genres": [
      {
        "id": 4,
        "name": "Comedy"
      },
      {
        "id": 22,
        "name": "Romance"
      }
    ],
    "demographics": [
      {
        "id": 27,
        "name": "Shounen"
      }
    ],
    "title_localized": null,
    "manga_url": "/manga/112807/Boku_no_Kokoro_no_Yabai_Yatsu",
    "manga_image_path": "https://cdn.myanimelist.net/r/192x272/images/manga/3/213349.jpg?s=2fb10df8a9df64f88289b1eb87d46acf",
    "is_added_to_list": false,
    "manga_media_type_string": "Manga",
    "start_date_string": "09-03-22",
    "finish_date_string": null,
    "manga_start_date_string": "03-08-18",
    "manga_end_date_string": null,
    "days_string": 689,
    "retail_string": null,
    "priority_string": "Low",
    "notes": "",
    "editable_notes": ""
  },
  {
    "id": 141342149,
    "status": 1,
    "score": 0,
    "tags": "",
    "is_rereading": 0,
    "num_read_chapters": 33,
    "num_read_volumes": 0,
    "created_at": 1678556589,
    "manga_title": "Dosanko Gal wa Namara Menkoi",
    "manga_english": "Hokkaido Gals Are Super Adorable!",
    "manga_num_chapters": 0,
    "manga_num_volumes": 0,
    "manga_publishing_status": 1,
    "manga_id": 121597,
    "manga_magazines": null,
    "manga_total_members": 36487,
    "manga_total_scores": 11551,
    "manga_score_val": 7.1,
    "manga_score_diff": -99,
    "manga_popularity": 482,
    "genres": [
      {
        "id": 4,
        "name": "Comedy"
      }
    ],
    "demographics": [
      {
        "id": 27,
        "name": "Shounen"
      }
    ],
    "title_localized": null,
    "manga_url": "/manga/121597/Dosanko_Gal_wa_Namara_Menkoi",
    "manga_image_path": "https://cdn.myanimelist.net/r/192x272/images/manga/1/224525.jpg?s=59756ba3a11b826535b806101b6355ec",
    "is_added_to_list": false,
    "manga_media_type_string": "Manga",
    "start_date_string": "03-11-23",
    "finish_date_string": null,
    "manga_start_date_string": "09-04-19",
    "manga_end_date_string": null,
    "days_string": 500,
    "retail_string": null,
    "priority_string": "Low",
    "notes": "",
    "editable_notes": ""
  },
  {
    "id": 141342161,
    "status": 1,
    "score": 0,
    "tags": "",
    "is_rereading": 0,
    "num_read_chapters": 42,
    "num_read_volumes": 0,
    "created_at": 1678556634,
    "manga_title": "Haite Kudasai, Takamine-san",
    "manga_english": "Please Put Them On, Takamine-san",
    "manga_num_chapters": 0,
    "manga_num_volumes": 0,
    "manga_publishing_status": 1,
    "manga_id": 121433,
    "manga_magazines": null,
    "manga_total_members": 38778,
    "manga_total_scores": 10736,
    "manga_score_val": 6.73,
    "manga_score_diff": -99,
    "manga_popularity": 459,
    "genres": [
      {
        "id": 4,
        "name": "Comedy"
      },
      {
        "id": 22,
        "name": "Romance"
      },
      {
        "id": 9,
        "name": "Ecchi"
      }
    ],
    "demographics": [
      {
        "id": 27,
        "name": "Shounen"
      }
    ],
    "title_localized": null,
    "manga_url": "/manga/121433/Haite_Kudasai_Takamine-san",
    "manga_image_path": "https://cdn.myanimelist.net/r/192x272/images/manga/1/222075.jpg?s=7335a04aa51f928d9fda533faf8f5c85",
    "is_added_to_list": false,
    "manga_media_type_string": "Manga",
    "start_date_string": "03-11-23",
    "finish_date_string": null,
    "manga_start_date_string": "01-22-19",
    "manga_end_date_string": null,
    "days_string": 500,
    "retail_string": null,
    "priority_string": "Low",
    "notes": "",
    "editable_notes": ""
  },
  {
    "id": 129261286,
    "status": 1,
    "score": 0,
    "tags": "",
    "is_rereading": 0,
    "num_read_chapters": 43,
    "num_read_volumes": 0,
    "created_at": 1657569000,
    "manga_title": "Hajirau Kimi ga Mitainda",
    "manga_english": "",
    "manga_num_chapters": 0,
    "manga_num_volumes": 0,
    "manga_publishing_status": 1,
    "manga_id": 134339,
    "manga_magazines": null,
    "manga_total_members": 12395,
    "manga_total_scores": 2921,
    "manga_score_val": 6.76,
    "manga_score_diff": -99,
    "manga_popularity": 1648,
    "genres": [
      {
        "id": 49,
        "name": "Erotica"
      }
    ],
    "demographics": [],
    "title_localized": null,
    "manga_url": "/manga/134339/Hajirau_Kimi_ga_Mitainda",
    "manga_image_path": "https://cdn.myanimelist.net/r/192x272/images/manga/2/255513.jpg?s=b4dae495e02f28784818dc9daf404d89",
    "is_added_to_list": false,
    "manga_media_type_string": "Manga",
    "start_date_string": "07-11-22",
    "finish_date_string": null,
    "manga_start_date_string": "01-15-21",
    "manga_end_date_string": null,
    "days_string": 743,
    "retail_string": null,
    "priority_string": "Low",
    "notes": "",
    "editable_notes": ""
  },
  {
    "id": 116780107,
    "status": 1,
    "score": 0,
    "tags": "",
    "is_rereading": 0,
    "num_read_chapters": 126,
    "num_read_volumes": 13,
    "created_at": 1636471343,
    "manga_title": "Ijiranaide, Nagatoro-san",
    "manga_english": "Don't Toy With Me, Miss Nagatoro",
    "manga_num_chapters": 0,
    "manga_num_volumes": 0,
    "manga_publishing_status": 1,
    "manga_id": 110737,
    "manga_magazines": null,
    "manga_total_members": 170766,
    "manga_total_scores": 75066,
    "manga_score_val": 7.62,
    "manga_score_diff": -99,
    "manga_popularity": 57,
    "genres": [
      {
        "id": 4,
        "name": "Comedy"
      },
      {
        "id": 36,
        "name": "Slice of Life"
      }
    ],
    "demographics": [],
    "title_localized": null,
    "manga_url": "/manga/110737/Ijiranaide_Nagatoro-san",
    "manga_image_path": "https://cdn.myanimelist.net/r/192x272/images/manga/1/268387.jpg?s=75168db7f0ff95394db870ca20893066",
    "is_added_to_list": false,
    "manga_media_type_string": "Manga",
    "start_date_string": "04-08-22",
    "finish_date_string": null,
    "manga_start_date_string": "11-07-17",
    "manga_end_date_string": null,
    "days_string": 837,
    "retail_string": null,
    "priority_string": "Low",
    "notes": "",
    "editable_notes": ""
  },
  {
    "id": 126692576,
    "status": 1,
    "score": 0,
    "tags": "",
    "is_rereading": 0,
    "num_read_chapters": 138,
    "num_read_volumes": 0,
    "created_at": 1653366464,
    "manga_title": "Kaette Kudasai! Akutsu-san",
    "manga_english": "Please Go Home, Miss Akutsu!",
    "manga_num_chapters": 0,
    "manga_num_volumes": 0,
    "manga_publishing_status": 1,
    "manga_id": 122353,
    "manga_magazines": null,
    "manga_total_members": 46929,
    "manga_total_scores": 16883,
    "manga_score_val": 7.37,
    "manga_score_diff": -99,
    "manga_popularity": 367,
    "genres": [
      {
        "id": 4,
        "name": "Comedy"
      }
    ],
    "demographics": [],
    "title_localized": null,
    "manga_url": "/manga/122353/Kaette_Kudasai_Akutsu-san",
    "manga_image_path": "https://cdn.myanimelist.net/r/192x272/images/manga/2/305251.jpg?s=a668eb86422232b6fccb61829577c5ef",
    "is_added_to_list": false,
    "manga_media_type_string": "Manga",
    "start_date_string": "05-23-22",
    "finish_date_string": null,
    "manga_start_date_string": "07-29-19",
    "manga_end_date_string": null,
    "days_string": 792,
    "retail_string": null,
    "priority_string": "Low",
    "notes": "",
    "editable_notes": ""
  },
  {
    "id": 143451184,
    "status": 1,
    "score": 0,
    "tags": "",
    "is_rereading": 0,
    "num_read_chapters": 20,
    "num_read_volumes": 0,
    "created_at": 1681444992,
    "manga_title": "Kaoru Hana wa Rin to Saku",
    "manga_english": "The Fragrant Flower Blooms with Dignity",
    "manga_num_chapters": 0,
    "manga_num_volumes": 0,
    "manga_publishing_status": 1,
    "manga_id": 144267,
    "manga_magazines": null,
    "manga_total_members": 59907,
    "manga_total_scores": 18987,
    "manga_score_val": 8.65,
    "manga_score_diff": -99,
    "manga_popularity": 273,
    "genres": [
      {
        "id": 8,
        "name": "Drama"
      },
      {
        "id": 22,
        "name": "Romance"
      }
    ],
    "demographics": [],
    "title_localized": null,
    "manga_url": "/manga/144267/Kaoru_Hana_wa_Rin_to_Saku",
    "manga_image_path": "https://cdn.myanimelist.net/r/192x272/images/manga/5/256607.jpg?s=5a3c47486c78c51d877857509f2d6e4b",
    "is_added_to_list": false,
    "manga_media_type_string": "Manga",
    "start_date_string": "04-13-23",
    "finish_date_string": null,
    "manga_start_date_string": "10-21-21",
    "manga_end_date_string": null,
    "days_string": 467,
    "retail_string": null,
    "priority_string": "Low",
    "notes": "",
    "editable_notes": ""
  },
  {
    "id": 124279933,
    "status": 1,
    "score": 0,
    "tags": "",
    "is_rereading": 0,
    "num_read_chapters": 272,
    "num_read_volumes": 0,
    "created_at": 1649465782,
    "manga_title": "Karakai Jouzu no (Moto) Takagi-san",
    "manga_english": "",
    "manga_num_chapters": 0,
    "manga_num_volumes": 0,
    "manga_publishing_status": 1,
    "manga_id": 108187,
    "manga_magazines": null,
    "manga_total_members": 45821,
    "manga_total_scores": 17228,
    "manga_score_val": 8.09,
    "manga_score_diff": -99,
    "manga_popularity": 377,
    "genres": [
      {
        "id": 4,
        "name": "Comedy"
      },
      {
        "id": 22,
        "name": "Romance"
      },
      {
        "id": 36,
        "name": "Slice of Life"
      }
    ],
    "demographics": [],
    "title_localized": null,
    "manga_url": "/manga/108187/Karakai_Jouzu_no_Moto_Takagi-san",
    "manga_image_path": "https://cdn.myanimelist.net/r/192x272/images/manga/2/204600.jpg?s=5b79ee08bc045c4f24a2e1d3a7c276c0",
    "is_added_to_list": false,
    "manga_media_type_string": "Manga",
    "start_date_string": "04-08-22",
    "finish_date_string": null,
    "manga_start_date_string": "07-15-17",
    "manga_end_date_string": null,
    "days_string": 837,
    "retail_string": null,
    "priority_string": "Low",
    "notes": "",
    "editable_notes": ""
  },
  {
    "id": 123362214,
    "status": 1,
    "score": 0,
    "tags": "",
    "is_rereading": 0,
    "num_read_chapters": 177,
    "num_read_volumes": 0,
    "created_at": 1647909067,
    "manga_title": "Kawaii dake ja Nai Shikimori-san",
    "manga_english": "Shikimori's Not Just a Cutie",
    "manga_num_chapters": 201,
    "manga_num_volumes": 20,
    "manga_publishing_status": 2,
    "manga_id": 118196,
    "manga_magazines": null,
    "manga_total_members": 66289,
    "manga_total_scores": 22017,
    "manga_score_val": 7.53,
    "manga_score_diff": -99,
    "manga_popularity": 244,
    "genres": [
      {
        "id": 4,
        "name": "Comedy"
      },
      {
        "id": 22,
        "name": "Romance"
      }
    ],
    "demographics": [],
    "title_localized": null,
    "manga_url": "/manga/118196/Kawaii_dake_ja_Nai_Shikimori-san",
    "manga_image_path": "https://cdn.myanimelist.net/r/192x272/images/manga/2/219606.jpg?s=5cbbd6a1321ed1f8a3a62d2514071f83",
    "is_added_to_list": false,
    "manga_media_type_string": "Manga",
    "start_date_string": "04-08-22",
    "finish_date_string": null,
    "manga_start_date_string": "02-02-19",
    "manga_end_date_string": "02-18-23",
    "days_string": 837,
    "retail_string": null,
    "priority_string": "Low",
    "notes": "",
    "editable_notes": ""
  },
  {
    "id": 123362288,
    "status": 1,
    "score": 0,
    "tags": "",
    "is_rereading": 0,
    "num_read_chapters": 399,
    "num_read_volumes": 0,
    "created_at": 1647909178,
    "manga_title": "Komi-san wa, Comyushou desu.",
    "manga_english": "Komi Can't Communicate",
    "manga_num_chapters": 0,
    "manga_num_volumes": 0,
    "manga_publishing_status": 1,
    "manga_id": 99007,
    "manga_magazines": null,
    "manga_total_members": 256097,
    "manga_total_scores": 100239,
    "manga_score_val": 8.09,
    "manga_score_diff": -99,
    "manga_popularity": 28,
    "genres": [
      {
        "id": 46,
        "name": "Award Winning"
      },
      {
        "id": 4,
        "name": "Comedy"
      }
    ],
    "demographics": [
      {
        "id": 27,
        "name": "Shounen"
      }
    ],
    "title_localized": null,
    "manga_url": "/manga/99007/Komi-san_wa_Comyushou_desu",
    "manga_image_path": "https://cdn.myanimelist.net/r/192x272/images/manga/3/188962.jpg?s=45af93199545922eea458ba23c815b48",
    "is_added_to_list": false,
    "manga_media_type_string": "Manga",
    "start_date_string": "04-08-22",
    "finish_date_string": null,
    "manga_start_date_string": "05-18-16",
    "manga_end_date_string": null,
    "days_string": 837,
    "retail_string": null,
    "priority_string": "Low",
    "notes": "",
    "editable_notes": ""
  },
  {
    "id": 132336593,
    "status": 1,
    "score": 0,
    "tags": "",
    "is_rereading": 0,
    "num_read_chapters": 41,
    "num_read_volumes": 0,
    "created_at": 1662601184,
    "manga_title": "Koori Zokusei Danshi to Cool na Douryou Joshi",
    "manga_english": "The Ice Guy and the Cool Girl",
    "manga_num_chapters": 0,
    "manga_num_volumes": 0,
    "manga_publishing_status": 1,
    "manga_id": 119082,
    "manga_magazines": null,
    "manga_total_members": 26802,
    "manga_total_scores": 6153,
    "manga_score_val": 7.68,
    "manga_score_diff": -99,
    "manga_popularity": 674,
    "genres": [
      {
        "id": 4,
        "name": "Comedy"
      },
      {
        "id": 10,
        "name": "Fantasy"
      },
      {
        "id": 22,
        "name": "Romance"
      }
    ],
    "demographics": [],
    "title_localized": null,
    "manga_url": "/manga/119082/Koori_Zokusei_Danshi_to_Cool_na_Douryou_Joshi",
    "manga_image_path": "https://cdn.myanimelist.net/r/192x272/images/manga/1/224869.jpg?s=65e839a2ce0cbc0948733d4ad36e421c",
    "is_added_to_list": false,
    "manga_media_type_string": "Manga",
    "start_date_string": "09-07-22",
    "finish_date_string": null,
    "manga_start_date_string": "07-22-19",
    "manga_end_date_string": null,
    "days_string": 685,
    "retail_string": null,
    "priority_string": "Low",
    "notes": "",
    "editable_notes": ""
  },
  {
    "id": 123362244,
    "status": 1,
    "score": 0,
    "tags": "",
    "is_rereading": 0,
    "num_read_chapters": 140,
    "num_read_volumes": 0,
    "created_at": 1647909126,
    "manga_title": "Kubo-san wa Mob wo Yurusanai",
    "manga_english": "Kubo Won't Let Me Be Invisible",
    "manga_num_chapters": 152,
    "manga_num_volumes": 12,
    "manga_publishing_status": 2,
    "manga_id": 122448,
    "manga_magazines": null,
    "manga_total_members": 67572,
    "manga_total_scores": 27817,
    "manga_score_val": 7.91,
    "manga_score_diff": -99,
    "manga_popularity": 237,
    "genres": [
      {
        "id": 4,
        "name": "Comedy"
      }
    ],
    "demographics": [
      {
        "id": 41,
        "name": "Seinen"
      }
    ],
    "title_localized": null,
    "manga_url": "/manga/122448/Kubo-san_wa_Mob_wo_Yurusanai",
    "manga_image_path": "https://cdn.myanimelist.net/r/192x272/images/manga/3/227284.jpg?s=80a965562614fece2464bd98a7b91fe8",
    "is_added_to_list": false,
    "manga_media_type_string": "Manga",
    "start_date_string": "04-08-22",
    "finish_date_string": null,
    "manga_start_date_string": "10-24-19",
    "manga_end_date_string": "03-02-23",
    "days_string": 837,
    "retail_string": null,
    "priority_string": "Low",
    "notes": "",
    "editable_notes": ""
  },
  {
    "id": 123362311,
    "status": 1,
    "score": 0,
    "tags": "",
    "is_rereading": 0,
    "num_read_chapters": 113,
    "num_read_volumes": 0,
    "created_at": 1647909195,
    "manga_title": "Mijuku na Futari de Gozaimasu ga",
    "manga_english": "We're New at This",
    "manga_num_chapters": 0,
    "manga_num_volumes": 0,
    "manga_publishing_status": 1,
    "manga_id": 113938,
    "manga_magazines": null,
    "manga_total_members": 26326,
    "manga_total_scores": 7558,
    "manga_score_val": 7.47,
    "manga_score_diff": -99,
    "manga_popularity": 693,
    "genres": [
      {
        "id": 4,
        "name": "Comedy"
      },
      {
        "id": 22,
        "name": "Romance"
      },
      {
        "id": 36,
        "name": "Slice of Life"
      }
    ],
    "demographics": [],
    "title_localized": null,
    "manga_url": "/manga/113938/Mijuku_na_Futari_de_Gozaimasu_ga",
    "manga_image_path": "https://cdn.myanimelist.net/r/192x272/images/manga/2/213271.jpg?s=9332ef661b4f2958ec675ae8c3d1524f",
    "is_added_to_list": false,
    "manga_media_type_string": "Manga",
    "start_date_string": "04-21-22",
    "finish_date_string": null,
    "manga_start_date_string": "03-09-18",
    "manga_end_date_string": null,
    "days_string": 824,
    "retail_string": null,
    "priority_string": "Low",
    "notes": "",
    "editable_notes": ""
  },
  {
    "id": 125056631,
    "status": 1,
    "score": 0,
    "tags": "",
    "is_rereading": 0,
    "num_read_chapters": 10,
    "num_read_volumes": 0,
    "created_at": 1650597735,
    "manga_title": "Otonari no Tenshi-sama ni Itsunomanika Dame Ningen ni Sareteita Ken",
    "manga_english": "The Angel Next Door Spoils Me Rotten",
    "manga_num_chapters": 0,
    "manga_num_volumes": 0,
    "manga_publishing_status": 1,
    "manga_id": 130934,
    "manga_magazines": null,
    "manga_total_members": 13236,
    "manga_total_scores": 3260,
    "manga_score_val": 7.97,
    "manga_score_diff": -99,
    "manga_popularity": 1541,
    "genres": [
      {
        "id": 4,
        "name": "Comedy"
      },
      {
        "id": 22,
        "name": "Romance"
      }
    ],
    "demographics": [],
    "title_localized": null,
    "manga_url": "/manga/130934/Otonari_no_Tenshi-sama_ni_Itsunomanika_Dame_Ningen_ni_Sareteita_Ken",
    "manga_image_path": "https://cdn.myanimelist.net/r/192x272/images/manga/2/265701.jpg?s=93b3905d8d0f774c3f99e78d549195fa",
    "is_added_to_list": false,
    "manga_media_type_string": "Manga",
    "start_date_string": "04-21-22",
    "finish_date_string": null,
    "manga_start_date_string": "01-06-22",
    "manga_end_date_string": null,
    "days_string": 824,
    "retail_string": null,
    "priority_string": "Low",
    "notes": "",
    "editable_notes": ""
  },
  {
    "id": 128017394,
    "status": 1,
    "score": 0,
    "tags": "",
    "is_rereading": 0,
    "num_read_chapters": 157,
    "num_read_volumes": 0,
    "created_at": 1655703618,
    "manga_title": "Real mo Tama ni wa Uso wo Tsuku",
    "manga_english": "Sometimes Even Reality Is a Lie!",
    "manga_num_chapters": 0,
    "manga_num_volumes": 0,
    "manga_publishing_status": 1,
    "manga_id": 124209,
    "manga_magazines": null,
    "manga_total_members": 21577,
    "manga_total_scores": 6655,
    "manga_score_val": 7.49,
    "manga_score_diff": -99,
    "manga_popularity": 866,
    "genres": [
      {
        "id": 4,
        "name": "Comedy"
      },
      {
        "id": 22,
        "name": "Romance"
      }
    ],
    "demographics": [],
    "title_localized": null,
    "manga_url": "/manga/124209/Real_mo_Tama_ni_wa_Uso_wo_Tsuku",
    "manga_image_path": "https://cdn.myanimelist.net/r/192x272/images/manga/3/257504.jpg?s=359334c1801dcee341fd4b19275156bb",
    "is_added_to_list": false,
    "manga_media_type_string": "Manga",
    "start_date_string": "06-19-22",
    "finish_date_string": null,
    "manga_start_date_string": "08-12-18",
    "manga_end_date_string": null,
    "days_string": 765,
    "retail_string": null,
    "priority_string": "Low",
    "notes": "",
    "editable_notes": ""
  },
  {
    "id": 123362277,
    "status": 1,
    "score": 0,
    "tags": "",
    "is_rereading": 0,
    "num_read_chapters": 195,
    "num_read_volumes": 0,
    "created_at": 1647909165,
    "manga_title": "Soredemo Ayumu wa Yosetekuru",
    "manga_english": "When Will Ayumu Make His Move?",
    "manga_num_chapters": 225,
    "manga_num_volumes": 17,
    "manga_publishing_status": 2,
    "manga_id": 119216,
    "manga_magazines": null,
    "manga_total_members": 36107,
    "manga_total_scores": 12504,
    "manga_score_val": 7.49,
    "manga_score_diff": -99,
    "manga_popularity": 488,
    "genres": [
      {
        "id": 4,
        "name": "Comedy"
      },
      {
        "id": 36,
        "name": "Slice of Life"
      }
    ],
    "demographics": [
      {
        "id": 27,
        "name": "Shounen"
      }
    ],
    "title_localized": null,
    "manga_url": "/manga/119216/Soredemo_Ayumu_wa_Yosetekuru",
    "manga_image_path": "https://cdn.myanimelist.net/r/192x272/images/manga/1/219724.jpg?s=11ff0b94134154d67ee14d307c28fbcb",
    "is_added_to_list": false,
    "manga_media_type_string": "Manga",
    "start_date_string": "04-08-22",
    "finish_date_string": null,
    "manga_start_date_string": "03-06-19",
    "manga_end_date_string": "11-15-23",
    "days_string": 837,
    "retail_string": null,
    "priority_string": "Low",
    "notes": "",
    "editable_notes": ""
  },
  {
    "id": 132336583,
    "status": 1,
    "score": 0,
    "tags": "",
    "is_rereading": 0,
    "num_read_chapters": 98,
    "num_read_volumes": 0,
    "created_at": 1662601147,
    "manga_title": "Suki na Ko ga Megane wo Wasureta",
    "manga_english": "The Girl I Like Forgot Her Glasses",
    "manga_num_chapters": 120,
    "manga_num_volumes": 12,
    "manga_publishing_status": 2,
    "manga_id": 117332,
    "manga_magazines": null,
    "manga_total_members": 40128,
    "manga_total_scores": 13660,
    "manga_score_val": 8.04,
    "manga_score_diff": -99,
    "manga_popularity": 440,
    "genres": [
      {
        "id": 4,
        "name": "Comedy"
      }
    ],
    "demographics": [
      {
        "id": 27,
        "name": "Shounen"
      }
    ],
    "title_localized": null,
    "manga_url": "/manga/117332/Suki_na_Ko_ga_Megane_wo_Wasureta",
    "manga_image_path": "https://cdn.myanimelist.net/r/192x272/images/manga/3/219461.jpg?s=00c43a955f9e8e7fc75bbb678c655a2f",
    "is_added_to_list": false,
    "manga_media_type_string": "Manga",
    "start_date_string": "09-07-22",
    "finish_date_string": null,
    "manga_start_date_string": "11-22-18",
    "manga_end_date_string": "04-22-24",
    "days_string": 685,
    "retail_string": null,
    "priority_string": "Low",
    "notes": "",
    "editable_notes": ""
  },
  {
    "id": 129261307,
    "status": 1,
    "score": 0,
    "tags": "",
    "is_rereading": 0,
    "num_read_chapters": 167,
    "num_read_volumes": 0,
    "created_at": 1657569024,
    "manga_title": "Yofukashi no Uta",
    "manga_english": "Call of the Night",
    "manga_num_chapters": 203,
    "manga_num_volumes": 20,
    "manga_publishing_status": 2,
    "manga_id": 121480,
    "manga_magazines": null,
    "manga_total_members": 92829,
    "manga_total_scores": 33333,
    "manga_score_val": 8.17,
    "manga_score_diff": -99,
    "manga_popularity": 155,
    "genres": [
      {
        "id": 46,
        "name": "Award Winning"
      },
      {
        "id": 22,
        "name": "Romance"
      },
      {
        "id": 37,
        "name": "Supernatural"
      }
    ],
    "demographics": [
      {
        "id": 27,
        "name": "Shounen"
      }
    ],
    "title_localized": null,
    "manga_url": "/manga/121480/Yofukashi_no_Uta",
    "manga_image_path": "https://cdn.myanimelist.net/r/192x272/images/manga/3/224212.jpg?s=49252dfca0797f9e712748981934b2fc",
    "is_added_to_list": false,
    "manga_media_type_string": "Manga",
    "start_date_string": "07-11-22",
    "finish_date_string": null,
    "manga_start_date_string": "08-28-19",
    "manga_end_date_string": "01-24-24",
    "days_string": 743,
    "retail_string": null,
    "priority_string": "Low",
    "notes": "",
    "editable_notes": ""
  },
  {
    "id": 128017410,
    "status": 1,
    "score": 0,
    "tags": "",
    "is_rereading": 0,
    "num_read_chapters": 61,
    "num_read_volumes": 0,
    "created_at": 1655703634,
    "manga_title": "Yozakura-san Chi no Daisakusen",
    "manga_english": "Mission: Yozakura Family",
    "manga_num_chapters": 0,
    "manga_num_volumes": 0,
    "manga_publishing_status": 1,
    "manga_id": 121426,
    "manga_magazines": null,
    "manga_total_members": 34183,
    "manga_total_scores": 10703,
    "manga_score_val": 7.65,
    "manga_score_diff": -99,
    "manga_popularity": 526,
    "genres": [
      {
        "id": 1,
        "name": "Action"
      },
      {
        "id": 4,
        "name": "Comedy"
      }
    ],
    "demographics": [
      {
        "id": 27,
        "name": "Shounen"
      }
    ],
    "title_localized": null,
    "manga_url": "/manga/121426/Yozakura-san_Chi_no_Daisakusen",
    "manga_image_path": "https://cdn.myanimelist.net/r/192x272/images/manga/1/226602.jpg?s=243b4e9c1cf1877e502c79307a0f066b",
    "is_added_to_list": false,
    "manga_media_type_string": "Manga",
    "start_date_string": "06-19-22",
    "finish_date_string": null,
    "manga_start_date_string": "08-26-19",
    "manga_end_date_string": null,
    "days_string": 765,
    "retail_string": null,
    "priority_string": "Low",
    "notes": "",
    "editable_notes": ""
  },
  {
    "id": 127112005,
    "status": 1,
    "score": 0,
    "tags": "",
    "is_rereading": 0,
    "num_read_chapters": 34,
    "num_read_volumes": 0,
    "created_at": 1654103800,
    "manga_title": "Yubisaki to Renren",
    "manga_english": "A Sign of Affection",
    "manga_num_chapters": 0,
    "manga_num_volumes": 0,
    "manga_publishing_status": 1,
    "manga_id": 121504,
    "manga_magazines": null,
    "manga_total_members": 49363,
    "manga_total_scores": 12454,
    "manga_score_val": 8.5,
    "manga_score_diff": -99,
    "manga_popularity": 337,
    "genres": [
      {
        "id": 22,
        "name": "Romance"
      }
    ],
    "demographics": [
      {
        "id": 25,
        "name": "Shoujo"
      }
    ],
    "title_localized": null,
    "manga_url": "/manga/121504/Yubisaki_to_Renren",
    "manga_image_path": "https://cdn.myanimelist.net/r/192x272/images/manga/5/262471.jpg?s=033a9a4cba05a876e1d8b23bbece7eed",
    "is_added_to_list": false,
    "manga_media_type_string": "Manga",
    "start_date_string": "06-01-22",
    "finish_date_string": null,
    "manga_start_date_string": "07-24-19",
    "manga_end_date_string": null,
    "days_string": 783,
    "retail_string": null,
    "priority_string": "Low",
    "notes": "",
    "editable_notes": ""
  },
  {
    "id": 132336549,
    "status": 2,
    "score": 0,
    "tags": "",
    "is_rereading": 0,
    "num_read_chapters": 107,
    "num_read_volumes": 0,
    "created_at": 1662601053,
    "manga_title": "A Royal Princess with Black Hair",
    "manga_english": "A Royal Princess with Black Hair",
    "manga_num_chapters": 107,
    "manga_num_volumes": 0,
    "manga_publishing_status": 2,
    "manga_id": 134065,
    "manga_magazines": null,
    "manga_total_members": 2822,
    "manga_total_scores": 926,
    "manga_score_val": 7.15,
    "manga_score_diff": -99,
    "manga_popularity": 6968,
    "genres": [
      {
        "id": 4,
        "name": "Comedy"
      },
      {
        "id": 10,
        "name": "Fantasy"
      },
      {
        "id": 22,
        "name": "Romance"
      }
    ],
    "demographics": [],
    "title_localized": null,
    "manga_url": "/manga/134065/A_Royal_Princess_with_Black_Hair",
    "manga_image_path": "https://cdn.myanimelist.net/r/192x272/images/manga/1/245710.jpg?s=0521e67b809231584c62177524a85f29",
    "is_added_to_list": false,
    "manga_media_type_string": "Manhwa",
    "start_date_string": "09-07-22",
    "finish_date_string": "03-16-24",
    "manga_start_date_string": "11-15-19",
    "manga_end_date_string": "06-02-23",
    "days_string": 557,
    "retail_string": null,
    "priority_string": "Low",
    "notes": "",
    "editable_notes": ""
  },
  {
    "id": 165959841,
    "status": 2,
    "score": 0,
    "tags": "",
    "is_rereading": 0,
    "num_read_chapters": 29,
    "num_read_volumes": 3,
    "created_at": 1721445785,
    "manga_title": "Chiisai Boku no Haru",
    "manga_english": "Spring of Little Me",
    "manga_num_chapters": 29,
    "manga_num_volumes": 3,
    "manga_publishing_status": 2,
    "manga_id": 157541,
    "manga_magazines": null,
    "manga_total_members": 1936,
    "manga_total_scores": 589,
    "manga_score_val": 6.59,
    "manga_score_diff": -99,
    "manga_popularity": 9408,
    "genres": [
      {
        "id": 4,
        "name": "Comedy"
      },
      {
        "id": 22,
        "name": "Romance"
      },
      {
        "id": 30,
        "name": "Sports"
      }
    ],
    "demographics": [
      {
        "id": 27,
        "name": "Shounen"
      }
    ],
    "title_localized": null,
    "manga_url": "/manga/157541/Chiisai_Boku_no_Haru",
    "manga_image_path": "https://cdn.myanimelist.net/r/192x272/images/manga/2/287144.jpg?s=8e40510fa4b9920d399e33568c21f4da",
    "is_added_to_list": false,
    "manga_media_type_string": "Manga",
    "start_date_string": null,
    "finish_date_string": "07-19-24",
    "manga_start_date_string": "05-10-23",
    "manga_end_date_string": "06-29-24",
    "days_string": null,
    "retail_string": null,
    "priority_string": "Low",
    "notes": "",
    "editable_notes": ""
  },
  {
    "id": 123362336,
    "status": 2,
    "score": 0,
    "tags": "",
    "is_rereading": 0,
    "num_read_chapters": 125,
    "num_read_volumes": 16,
    "created_at": 1647909244,
    "manga_title": "Horimiya",
    "manga_english": "Horimiya",
    "manga_num_chapters": 139,
    "manga_num_volumes": 17,
    "manga_publishing_status": 2,
    "manga_id": 42451,
    "manga_magazines": null,
    "manga_total_members": 338825,
    "manga_total_scores": 152668,
    "manga_score_val": 8.42,
    "manga_score_diff": -99,
    "manga_popularity": 16,
    "genres": [
      {
        "id": 22,
        "name": "Romance"
      }
    ],
    "demographics": [
      {
        "id": 27,
        "name": "Shounen"
      }
    ],
    "title_localized": null,
    "manga_url": "/manga/42451/Horimiya",
    "manga_image_path": "https://cdn.myanimelist.net/r/192x272/images/manga/2/245008.jpg?s=951dec7109b4685ed4fc168e0933291f",
    "is_added_to_list": false,
    "manga_media_type_string": "Manga",
    "start_date_string": null,
    "finish_date_string": null,
    "manga_start_date_string": "10-18-11",
    "manga_end_date_string": "03-18-21",
    "days_string": null,
    "retail_string": null,
    "priority_string": "Low",
    "notes": "",
    "editable_notes": ""
  },
  {
    "id": 123362225,
    "status": 2,
    "score": 0,
    "tags": "",
    "is_rereading": 0,
    "num_read_chapters": 281,
    "num_read_volumes": 28,
    "created_at": 1647909099,
    "manga_title": "Kaguya-sama wa Kokurasetai: Tensai-tachi no Renai Zunousen",
    "manga_english": "Kaguya-sama: Love Is War",
    "manga_num_chapters": 281,
    "manga_num_volumes": 28,
    "manga_publishing_status": 2,
    "manga_id": 90125,
    "manga_magazines": null,
    "manga_total_members": 274033,
    "manga_total_scores": 133952,
    "manga_score_val": 8.9,
    "manga_score_diff": -99,
    "manga_popularity": 23,
    "genres": [
      {
        "id": 46,
        "name": "Award Winning"
      },
      {
        "id": 4,
        "name": "Comedy"
      }
    ],
    "demographics": [
      {
        "id": 41,
        "name": "Seinen"
      }
    ],
    "title_localized": null,
    "manga_url": "/manga/90125/Kaguya-sama_wa_Kokurasetai__Tensai-tachi_no_Renai_Zunousen",
    "manga_image_path": "https://cdn.myanimelist.net/r/192x272/images/manga/3/188896.jpg?s=a2844cb4d66895f66a46a15ac776d0de",
    "is_added_to_list": false,
    "manga_media_type_string": "Manga",
    "start_date_string": "04-08-22",
    "finish_date_string": null,
    "manga_start_date_string": "05-19-15",
    "manga_end_date_string": "11-02-22",
    "days_string": 837,
    "retail_string": null,
    "priority_string": "Low",
    "notes": "",
    "editable_notes": ""
  },
  {
    "id": 123362330,
    "status": 2,
    "score": 0,
    "tags": "",
    "is_rereading": 0,
    "num_read_chapters": 222,
    "num_read_volumes": 16,
    "created_at": 1647909229,
    "manga_title": "Shinigami Bocchan to Kuro Maid",
    "manga_english": "The Duke of Death and His Maid",
    "manga_num_chapters": 242,
    "manga_num_volumes": 16,
    "manga_publishing_status": 2,
    "manga_id": 110029,
    "manga_magazines": null,
    "manga_total_members": 30665,
    "manga_total_scores": 10045,
    "manga_score_val": 7.85,
    "manga_score_diff": -99,
    "manga_popularity": 585,
    "genres": [
      {
        "id": 4,
        "name": "Comedy"
      },
      {
        "id": 8,
        "name": "Drama"
      }
    ],
    "demographics": [],
    "title_localized": null,
    "manga_url": "/manga/110029/Shinigami_Bocchan_to_Kuro_Maid",
    "manga_image_path": "https://cdn.myanimelist.net/r/192x272/images/manga/2/205563.jpg?s=605cdd07322723ef7cc4447f9540c2b6",
    "is_added_to_list": false,
    "manga_media_type_string": "Manga",
    "start_date_string": "04-08-22",
    "finish_date_string": "06-19-22",
    "manga_start_date_string": "10-03-17",
    "manga_end_date_string": "05-17-22",
    "days_string": 73,
    "retail_string": null,
    "priority_string": "Low",
    "notes": "",
    "editable_notes": ""
  },
  {
    "id": 123362349,
    "status": 2,
    "score": 0,
    "tags": "",
    "is_rereading": 0,
    "num_read_chapters": 325,
    "num_read_volumes": 36,
    "created_at": 1647909261,
    "manga_title": "Shokugeki no Souma",
    "manga_english": "Food Wars!: Shokugeki no Soma",
    "manga_num_chapters": 325,
    "manga_num_volumes": 36,
    "manga_publishing_status": 2,
    "manga_id": 45757,
    "manga_magazines": null,
    "manga_total_members": 179482,
    "manga_total_scores": 89480,
    "manga_score_val": 7.91,
    "manga_score_diff": -99,
    "manga_popularity": 47,
    "genres": [
      {
        "id": 47,
        "name": "Gourmet"
      },
      {
        "id": 9,
        "name": "Ecchi"
      }
    ],
    "demographics": [
      {
        "id": 27,
        "name": "Shounen"
      }
    ],
    "title_localized": null,
    "manga_url": "/manga/45757/Shokugeki_no_Souma",
    "manga_image_path": "https://cdn.myanimelist.net/r/192x272/images/manga/1/115803.jpg?s=5d9c60c78970bb75b8ee5fef8e339f9a",
    "is_added_to_list": false,
    "manga_media_type_string": "Manga",
    "start_date_string": null,
    "finish_date_string": null,
    "manga_start_date_string": "11-26-12",
    "manga_end_date_string": "08-29-19",
    "days_string": null,
    "retail_string": null,
    "priority_string": "Low",
    "notes": "",
    "editable_notes": ""
  },
  {
    "id": 133650056,
    "status": 2,
    "score": 0,
    "tags": "",
    "is_rereading": 0,
    "num_read_chapters": 57,
    "num_read_volumes": 0,
    "created_at": 1665267996,
    "manga_title": "Sore wa Rei no Shiwaza desu",
    "manga_english": "",
    "manga_num_chapters": 60,
    "manga_num_volumes": 7,
    "manga_publishing_status": 2,
    "manga_id": 126037,
    "manga_magazines": null,
    "manga_total_members": 12559,
    "manga_total_scores": 4568,
    "manga_score_val": 7.08,
    "manga_score_diff": -99,
    "manga_popularity": 1631,
    "genres": [
      {
        "id": 4,
        "name": "Comedy"
      },
      {
        "id": 37,
        "name": "Supernatural"
      }
    ],
    "demographics": [],
    "title_localized": null,
    "manga_url": "/manga/126037/Sore_wa_Rei_no_Shiwaza_desu",
    "manga_image_path": "https://cdn.myanimelist.net/r/192x272/images/manga/1/276838.jpg?s=f1d1d7bcdcacf379a4ab2d526ec63f25",
    "is_added_to_list": false,
    "manga_media_type_string": "Manga",
    "start_date_string": "10-08-22",
    "finish_date_string": "01-21-23",
    "manga_start_date_string": "04-04-20",
    "manga_end_date_string": "12-24-22",
    "days_string": 106,
    "retail_string": null,
    "priority_string": "Low",
    "notes": "",
    "editable_notes": ""
  },
  {
    "id": 132736983,
    "status": 2,
    "score": 0,
    "tags": "",
    "is_rereading": 0,
    "num_read_chapters": 40,
    "num_read_volumes": 0,
    "created_at": 1663440861,
    "manga_title": "Yankee JK Ayaka-san no Jakuten",
    "manga_english": "",
    "manga_num_chapters": 45,
    "manga_num_volumes": 2,
    "manga_publishing_status": 2,
    "manga_id": 142123,
    "manga_magazines": null,
    "manga_total_members": 3474,
    "manga_total_scores": 1316,
    "manga_score_val": 6.77,
    "manga_score_diff": -99,
    "manga_popularity": 5821,
    "genres": [
      {
        "id": 4,
        "name": "Comedy"
      }
    ],
    "demographics": [],
    "title_localized": null,
    "manga_url": "/manga/142123/Yankee_JK_Ayaka-san_no_Jakuten",
    "manga_image_path": "https://cdn.myanimelist.net/r/192x272/images/manga/1/259086.jpg?s=35add30d105d596e79416d2e4481ef40",
    "is_added_to_list": false,
    "manga_media_type_string": "Manga",
    "start_date_string": "09-17-22",
    "finish_date_string": "11-03-22",
    "manga_start_date_string": "08-01-21",
    "manga_end_date_string": "10-21-22",
    "days_string": 48,
    "retail_string": null,
    "priority_string": "Low",
    "notes": "",
    "editable_notes": ""
  },
  {
    "id": 123362265,
    "status": 3,
    "score": 0,
    "tags": "",
    "is_rereading": 0,
    "num_read_chapters": 168,
    "num_read_volumes": 18,
    "created_at": 1647909142,
    "manga_title": "Tonikaku Kawaii",
    "manga_english": "Fly Me to the Moon",
    "manga_num_chapters": 0,
    "manga_num_volumes": 0,
    "manga_publishing_status": 1,
    "manga_id": 112589,
    "manga_magazines": null,
    "manga_total_members": 85148,
    "manga_total_scores": 31207,
    "manga_score_val": 8.17,
    "manga_score_diff": -99,
    "manga_popularity": 179,
    "genres": [
      {
        "id": 4,
        "name": "Comedy"
      },
      {
        "id": 22,
        "name": "Romance"
      }
    ],
    "demographics": [
      {
        "id": 27,
        "name": "Shounen"
      }
    ],
    "title_localized": null,
    "manga_url": "/manga/112589/Tonikaku_Kawaii",
    "manga_image_path": "https://cdn.myanimelist.net/r/192x272/images/manga/3/209955.jpg?s=80a79ef8a5f4a4a6c7551957750ad955",
    "is_added_to_list": false,
    "manga_media_type_string": "Manga",
    "start_date_string": "04-08-22",
    "finish_date_string": null,
    "manga_start_date_string": "02-14-18",
    "manga_end_date_string": null,
    "days_string": 837,
    "retail_string": null,
    "priority_string": "Low",
    "notes": "",
    "editable_notes": ""
  }
]